sibr_agent/__init__.py
sibr_agent/base.py
sibr_agent/google_auth.py
sibr_agent/langchain_firestore.py
sibr_agent-0.1.8.dist-info/METADATA
sibr_agent-0.1.8.dist-info/WHEEL
sibr_agent-0.1.8.dist-info/top_level.txt
sibr_agent-0.1.8.dist-info/RECORD
