Metadata-Version: 2.4
Name: sibr-agent
Version: 0.1.8
Summary: Add your description here
Requires-Python: >=3.11
Requires-Dist: fastapi>=0.119.0
Requires-Dist: geopy>=2.4.1
Requires-Dist: google-cloud-bigquery>=3.38.0
Requires-Dist: google-cloud-firestore>=2.21.0
Requires-Dist: jose>=1.0.0
Requires-Dist: langchain>=0.3.27
Requires-Dist: langchain-community>=0.3.31
Requires-Dist: langchain-google-vertexai>=2.1.2
Requires-Dist: langchain-openai>=0.3.35
Requires-Dist: langchain-tavily>=0.2.12
Requires-Dist: langgraph>=0.6.10
Requires-Dist: pydantic>=2.12.0
Requires-Dist: pyjwt>=2.10.1
Requires-Dist: tiktoken>=0.12.0
